[
  {
    "email": "irygracia@gmail.com",
    "platform": "polpick",
    "timestamp": 1783963437806,
    "success": false,
    "bonus": 0
  },
  {
    "email": "irygracia@gmail.com",
    "platform": "polpick",
    "timestamp": 1783970738263,
    "success": false,
    "bonus": 0
  },
  {
    "email": "irygracia@gmail.com",
    "platform": "polpick",
    "timestamp": 1783978049492,
    "success": false,
    "bonus": 0
  },
  {
    "email": "irygracia@gmail.com",
    "platform": "polpick",
    "timestamp": 1783985382908,
    "success": false,
    "bonus": 0
  },
  {
    "email": "irygracia@gmail.com",
    "platform": "polpick",
    "timestamp": 1783992740756,
    "success": false,
    "bonus": 0
  },
  {
    "email": "irygracia@gmail.com",
    "platform": "polpick",
    "timestamp": 1784000067479,
    "success": false,
    "bonus": 0
  },
  {
    "email": "irygracia@gmail.com",
    "platform": "polpick",
    "timestamp": 1784007398577,
    "success": false,
    "bonus": 0
  },
  {
    "email": "irygracia@gmail.com",
    "platform": "polpick",
    "timestamp": 1784014738718,
    "success": false,
    "bonus": 0
  },
  {
    "email": "irygracia@gmail.com",
    "platform": "polpick",
    "timestamp": 1784018563677,
    "success": false,
    "bonus": 0
  },
  {
    "email": "irygracia@gmail.com",
    "platform": "polpick",
    "timestamp": 1784022410475,
    "success": false,
    "bonus": 0
  },
  {
    "email": "irygracia@gmail.com",
    "platform": "polpick",
    "timestamp": 1784026240502,
    "success": false,
    "bonus": 0
  },
  {
    "email": "irygracia@gmail.com",
    "platform": "polpick",
    "timestamp": 1784030059603,
    "success": false,
    "bonus": 0
  },
  {
    "email": "irygracia@gmail.com",
    "platform": "polpick",
    "timestamp": 1784033914574,
    "success": false,
    "bonus": 0
  },
  {
    "email": "irygracia@gmail.com",
    "platform": "polpick",
    "timestamp": 1784037750148,
    "success": false,
    "bonus": 0
  },
  {
    "email": "irygracia@gmail.com",
    "platform": "polpick",
    "timestamp": 1784041604925,
    "success": false,
    "bonus": 0
  },
  {
    "email": "irygracia@gmail.com",
    "platform": "polpick",
    "timestamp": 1784045441220,
    "success": false,
    "bonus": 0
  },
  {
    "email": "irygracia@gmail.com",
    "platform": "polpick",
    "timestamp": 1784049270508,
    "success": false,
    "bonus": 0
  },
  {
    "email": "irygracia@gmail.com",
    "platform": "polpick",
    "timestamp": 1784053119425,
    "success": false,
    "bonus": 0
  },
  {
    "email": "irygracia@gmail.com",
    "platform": "polpick",
    "timestamp": 1784056933195,
    "success": false,
    "bonus": 0
  },
  {
    "email": "irygracia@gmail.com",
    "platform": "polpick",
    "timestamp": 1784060748351,
    "success": false,
    "bonus": 0
  },
  {
    "email": "irygracia@gmail.com",
    "platform": "polpick",
    "timestamp": 1784064574276,
    "success": false,
    "bonus": 0
  },
  {
    "email": "irygracia@gmail.com",
    "platform": "polpick",
    "timestamp": 1784068418942,
    "success": false,
    "bonus": 0
  },
  {
    "email": "irygracia@gmail.com",
    "platform": "polpick",
    "timestamp": 1784072256808,
    "success": false,
    "bonus": 0
  },
  {
    "email": "irygracia@gmail.com",
    "platform": "polpick",
    "timestamp": 1784076142474,
    "success": false,
    "bonus": 0
  },
  {
    "email": "irygracia@gmail.com",
    "platform": "polpick",
    "timestamp": 1784080008074,
    "success": false,
    "bonus": 0
  }
]